MANIFEST.in
README.rst
setup.py
cielo/__init__.py
cielo/authorize.xml
cielo/capture.xml
cielo/main.py
cielo/util.py
python_cielo.egg-info/PKG-INFO
python_cielo.egg-info/SOURCES.txt
python_cielo.egg-info/dependency_links.txt
python_cielo.egg-info/not-zip-safe
python_cielo.egg-info/requires.txt
python_cielo.egg-info/top_level.txt