Metadata-Version: 1.1
Name: python-cielo
Version: 0.5
Summary: python-cielo is a lightweight lib for making payments over the Cielo webservice (Brazil)
Home-page: http://github.com/rpedigoni/python-cielo
Author: Renato Pedigoni
Author-email: renatopedigoni@gmail.com
License: BSD
Keywords: cielo e-commerce
Platform: UNKNOWN
Classifier: Programming Language :: Python
Classifier: Topic :: Software Development :: Libraries :: Python Modules
